LICENSE
MANIFEST.in
README.rst
setup.py
docs/Makefile
docs/changelog.rst
docs/conf.py
docs/index.rst
docs/make.bat
felmina/__init__.py
felmina/utils.py
felmina.egg-info/PKG-INFO
felmina.egg-info/SOURCES.txt
felmina.egg-info/dependency_links.txt
felmina.egg-info/not-zip-safe
felmina.egg-info/requires.txt
felmina.egg-info/top_level.txt
felmina/client/__init__.py
felmina/client/core.py
felmina/client/entity.py
felmina/client/namespaced.py
felmina/client/relation.py
felmina/client/schema.py
felmina/models/__init__.py
felmina/models/data.py
requirements/test.txt
tests/__init__.py
tests/conftest.py
tests/test_client/__init__.py
tests/test_client/test_entity_client.py
tests/test_client/test_relation_client.py
tests/test_client/test_schema_client.py