Metadata-Version: 1.2
Name: felmina
Version: 0.1.0
Summary: A tool for knowledge graph management based solely on Elasticsearch
Home-page: https://github.com/jadbin/felmina
Author: jadbin
Author-email: jadbin.com@hotmail.com
License: MIT
Platform: UNKNOWN
Classifier: License :: OSI Approved :: MIT License
Classifier: Intended Audience :: Developers
Classifier: Programming Language :: Python
Classifier: Programming Language :: Python :: 3
Classifier: Topic :: Software Development :: Libraries :: Python Modules
Requires-Python: >=3.6
